pymatrix123/__init__.py
pymatrix123/generalmatrix.py
pymatrix123/squarematrix.py
py_Matrix_123-0.0.3.dist-info/METADATA
py_Matrix_123-0.0.3.dist-info/WHEEL
py_Matrix_123-0.0.3.dist-info/top_level.txt
py_Matrix_123-0.0.3.dist-info/RECORD
