Metadata-Version: 2.1
Name: py-Matrix-123
Version: 0.0.3
Summary: A python package that retrieves matrix dimensions, their trace, and performs matrix addition, subtraction, multiplication.
Home-page: https://github.com/beauvilerobed/py-matrix-123
Author: Robed Beauvile
Author-email: robedbeauvil@gmail.com
License: UNKNOWN
Platform: UNKNOWN
